1stproject/timer.v
module timer(clk,timer_start,rst,timer_done);
input clk,timer_start,rst;
output reg timer_done;
parameter MAX=5;
reg [2:0] count = 3'b000;
always @(posedge clk or posedge rst)begin
if(rst==1) begin
count<=0;
timer_done<=0;
end 

else 
begin

if(timer_start==0)begin
count<=0;
timer_done<=0;
end 


else if(count==MAX-1 && timer_start==1) begin
timer_done<=1;
count <= 0;
end   

else if(timer_start==1 && count < MAX) begin
count<=count+1;
timer_done<=0;
end

end 

end 

endmodule

Elevator_Controller_FSM/floor_counter.v
module floor_counter(current_floor,rst,count_en,direction,clk);
input count_en,clk,rst ;
input [1:0] direction;
output reg [1:0]current_floor;
parameter UP = 2'b11;
parameter DOWN = 2'b01;
always @ (posedge clk or posedge rst)
begin
if(rst==1) begin
current_floor <= 0;
end 

else
begin
  if(count_en==1 && direction==UP)begin
current_floor <= current_floor+1;
end

  else if(count_en==1 && direction==DOWN)begin
current_floor <= current_floor-1;
end 

  else 
  begin
// do nothing
  end 

  end

  end  
 endmodule

Elevator_Controller_FSM/elevator.v
module elevator(count_en,direction,timer_start,clk,rst,current_floor,target_floor,timer_done);

input clk,rst,timer_done;
input [1:0] current_floor,target_floor;
output reg timer_start;
output reg count_en;
output reg[1:0] direction;
reg[1:0] current_state;
reg[1:0] next_state;
parameter IDLE = 2'b00;
parameter DOWN = 2'b01;
parameter UP = 2'b11;

always @ (posedge clk or posedge rst)
begin
if(rst==1)
  begin
  current_state <= IDLE;
end 

else
  begin
  current_state <= next_state;
  end
end

always @(*) 
begin
next_state=current_state;
count_en=0;
direction=IDLE;
timer_start=0;

if(current_state==IDLE)
begin
  if(current_floor==target_floor)
  begin
  next_state=IDLE;
  end

  else if(current_floor<target_floor)
  begin
  next_state=UP;
  direction = UP;
  timer_start=1;
  end

  else if(current_floor>target_floor)
  begin
  next_state=DOWN;
  direction = DOWN;
  timer_start=1;
  end 
  end

if(current_state==UP)
begin
direction=UP;
  if(timer_done==0)
  begin
  timer_start=1;
  end

  else if(timer_done==1 && current_floor+1<target_floor)
  begin
  next_state=UP;
  timer_start=1;
  count_en=1;
  end

  else if(timer_done==1 && current_floor+1==target_floor)
  begin
  next_state=IDLE;
  timer_start=0;
  count_en=1;
  end
  end

if(current_state==DOWN)
begin
direction=DOWN;
  if(timer_done==0)
  begin
    timer_start=1;
  end

  else if(timer_done==1 && current_floor-1>target_floor)
  begin
  next_state=DOWN;
  timer_start=1;
  count_en=1;
  end

  else if(timer_done==1 && current_floor-1==target_floor)
  begin
  next_state=IDLE;
  timer_start=0;
  count_en=1;
  end
  end

  end

  endmodule

1stproject/topmodule.v
module topmodule(clk,rst,button_0,button_1,button_2,button_3);

input button_0 , button_1 , button_2 , button_3 ;
input clk,rst;
wire [1:0]direction;
wire count_en,timer_start,timer_done;
wire [1:0] current_floor;
reg [1:0] target_floor;

always @ (posedge clk or posedge rst) begin
if(rst==1) begin
target_floor <= 2'b00;
end 

else begin
   if(button_0) target_floor <= 2'b00;
   else if(button_1) target_floor <= 2'b01;
   else if(button_2) target_floor <= 2'b10;
   else if(button_3) target_floor <= 2'b11;
   
  end 

  end

  elevator fsm(
    .current_floor(current_floor), 
    .target_floor(target_floor),  
    .timer_done(timer_done),       
    .count_en(count_en),           
    .direction(direction),         
    .timer_start(timer_start),    
    .clk(clk),
    .rst(rst)
);

floor_counter block1 (
    .current_floor(current_floor), 
    .count_en(count_en),         
    .direction(direction),         
    .clk(clk),
    .rst(rst)
);

timer block2 (
    .timer_done(timer_done),      
    .timer_start(timer_start),     
    .clk(clk),
    .rst(rst)
);

endmodule

Elevator_Controller_FSM/testbench.v
`timescale 1ns/1ps

module testbench;
reg clk,rst,button_0,button_1,button_2,button_3;

topmodule DUT(.clk(clk),.rst(rst),.button_0(button_0),.button_1(button_1),.button_2(button_2),.button_3(button_3));

always #5 clk = ~ clk;

initial 
begin
$dumpfile("topmodule.vcd");
$dumpvars(0, DUT);
end 

initial
 begin
 button_0=0;
 button_1=0;
 button_2=0;
 button_3=0;
 clk=0;
 rst=1;

 #20 rst = 0 ;
 
 #10 
 button_1=1;
 #10
 button_1=0;

 #200 // The time was chosen to be much larger than the time the elevator needs to move between floors which is nearly 50 ns , so to go from 0--->3 total 150ns
 #10 button_3=1;
 #10 button_3=0;

 #200 // The time was chosen to be much larger than the time the elevator needs to move between floors which is nearly 50 ns  , so to go from 0--->3 total 150ns

 #10 button_2=1;
 #10 button_2=0;

 #200 // The time was chosen to be much larger than the time the elevator needs to move between floors which is nearly 50 ns  , so to go from 0--->3 total 150ns
 #10 button_1=1;
 #10 button_1=0;
 
 # 2000 ;
 $finish;
 end
 endmodule

1stproject/topmodule.vcd
$date
	Mon Feb 09 14:10:07 2026
$end
$version
	Icarus Verilog
$end
$timescale
	1ps
$end
$scope module testbench $end
$scope module DUT $end
$var wire 1 ! button_0 $end
$var wire 1 " button_1 $end
$var wire 1 # button_2 $end
$var wire 1 $ button_3 $end
$var wire 1 % clk $end
$var wire 1 & rst $end
$var wire 1 ' timer_start $end
$var wire 1 ( timer_done $end
$var wire 2 ) direction [1:0] $end
$var wire 2 * current_floor [1:0] $end
$var wire 1 + count_en $end
$var reg 2 , target_floor [1:0] $end
$scope module block1 $end
$var wire 1 % clk $end
$var wire 1 & rst $end
$var wire 2 - direction [1:0] $end
$var wire 1 + count_en $end
$var parameter 2 . DOWN $end
$var parameter 2 / UP $end
$var reg 2 0 current_floor [1:0] $end
$upscope $end
$scope module block2 $end
$var wire 1 % clk $end
$var wire 1 & rst $end
$var wire 1 ' timer_start $end
$var parameter 32 1 MAX $end
$var reg 3 2 count [2:0] $end
$var reg 1 ( timer_done $end
$upscope $end
$scope module fsm $end
$var wire 1 % clk $end
$var wire 2 3 current_floor [1:0] $end
$var wire 1 & rst $end
$var wire 2 4 target_floor [1:0] $end
$var wire 1 ( timer_done $end
$var parameter 2 5 DOWN $end
$var parameter 2 6 IDLE $end
$var parameter 2 7 UP $end
$var reg 1 + count_en $end
$var reg 2 8 current_state [1:0] $end
$var reg 2 9 direction [1:0] $end
$var reg 2 : next_state [1:0] $end
$var reg 1 ' timer_start $end
$upscope $end
$upscope $end
$upscope $end
$enddefinitions $end
$comment Show the parameter values. $end
$dumpall
b11 7
b0 6
b1 5
b101 1
b11 /
b1 .
$end
#0
$dumpvars
b0 :
b0 9
b0 8
b0 4
b0 3
b0 2
b0 0
b0 -
b0 ,
0+
b0 *
b0 )
0(
0'
1&
0%
0$
0#
0"
0!
$end
#5000
1%
#10000
0%
#15000
1%
#20000
0%
0&
#25000
1%
#30000
0%
1"
#35000
1'
b11 )
b11 -
b11 9
b11 :
b1 ,
b1 4
1%
#40000
0%
0"
#45000
1'
b11 )
b11 -
b11 9
b1 2
b11 8
1%
#50000
0%
1$
#55000
1'
b11 )
b11 -
b11 9
b10 2
b11 ,
b11 4
1%
#60000
0%
0$
#65000
b11 2
1%
#70000
0%
#75000
b100 2
1%
#80000
0%
#85000
1+
1'
b11 )
b11 -
b11 9
b0 2
1(
1%
#90000
0%
#95000
1'
b11 )
b11 -
b11 9
0+
b1 *
b1 0
b1 3
0(
b1 2
1%
#100000
0%
#105000
b10 2
1%
#110000
0%
#115000
b11 2
1%
#120000
0%
#125000
b100 2
1%
#130000
0%
#135000
1+
1'
b11 )
b11 -
b11 9
b0 2
1(
1%
#140000
0%
#145000
1'
b11 )
b11 -
b11 9
0+
0(
b1 2
b10 *
b10 0
b10 3
1%
#150000
0%
#155000
b10 2
1%
#160000
0%
#165000
b11 2
1%
#170000
0%
#175000
b100 2
1%
#180000
0%
#185000
1+
b0 :
0'
b11 )
b11 -
b11 9
b0 2
1(
1%
#190000
0%
#195000
b0 )
b0 -
b0 9
0+
b0 8
b11 *
b11 0
b11 3
0(
1%
